{
  "legislative_session": "2025",
  "identifier": "HB829",
  "title": "RELATING TO INTOXICATING LIQUOR.",
  "from_organization": "~{\"classification\": \"lower\"}",
  "classification": [
    "bill"
  ],
  "subject": [
    "Criminal History Record Check",
    "Exempt",
    "Intoxicating Liquor",
    "Licenses",
    "Nonprofit Organizations"
  ],
  "abstracts": [
    {
      "note": "description",
      "abstract": "Provides that leaders of nonprofit organizations shall be exempt from county liquor commission criminal history check requirements for license applicants."
    }
  ],
  "other_titles": [],
  "other_identifiers": [],
  "actions": [
    {
      "description": "Referred to JHA, referral sheet 3",
      "date": "2025-01-23",
      "organization_id": "~{\"classification\": \"lower\"}",
      "classification": [
        "referral-committee"
      ],
      "related_entities": [
        {
          "name": "Judiciary & Hawaiian Affairs",
          "entity_type": "organization",
          "organization_id": null
        }
      ],
      "_processing": {
        "log_file_created": "2025-10-23T18:13:01Z"
      }
    },
    {
      "description": "Introduced and Pass First Reading.",
      "date": "2025-01-23",
      "organization_id": "~{\"classification\": \"lower\"}",
      "classification": [
        "introduction",
        "reading-1"
      ],
      "related_entities": [],
      "_processing": {
        "log_file_created": "2025-10-23T18:13:01Z"
      }
    },
    {
      "description": "Pending introduction.",
      "date": "2025-01-21",
      "organization_id": "~{\"classification\": \"lower\"}",
      "classification": [],
      "related_entities": [],
      "_processing": {
        "log_file_created": "2025-10-23T18:13:01Z"
      }
    }
  ],
  "sponsorships": [
    {
      "name": "MIYAKE",
      "classification": "primary",
      "entity_type": "person",
      "primary": true,
      "person_id": "~{\"name\": \"MIYAKE\"}",
      "organization_id": null
    },
    {
      "name": "LAMOSAO",
      "classification": "primary",
      "entity_type": "person",
      "primary": true,
      "person_id": "~{\"name\": \"LAMOSAO\"}",
      "organization_id": null
    }
  ],
  "related_bills": [
    {
      "identifier": "SB 100",
      "legislative_session": "2025 Regular Session",
      "relation_type": "companion"
    }
  ],
  "versions": [
    {
      "note": "HB829",
      "links": [
        {
          "url": "https://data.capitol.hawaii.gov/sessions//session2025/bills/HB829_.HTM",
          "media_type": "text/html"
        },
        {
          "url": "https://data.capitol.hawaii.gov/sessions//session2025/bills/HB829_.PDF",
          "media_type": "application/pdf"
        }
      ],
      "date": "",
      "classification": ""
    }
  ],
  "documents": [],
  "citations": [],
  "sources": [
    {
      "url": "https://capitol.hawaii.gov/session/measure_indiv.aspx?billtype=HB&billnumber=829&year=2025",
      "note": ""
    }
  ],
  "extras": {
    "current_referral": "JHA"
  },
  "jurisdiction": {
    "id": "ocd-jurisdiction/country:us/state:hi/government",
    "name": "Hawaii",
    "classification": "state",
    "division_id": "ocd-division/country:us/state:hi"
  },
  "_processing": {
    "logs_latest_update": "2025-10-23T18:13:01Z",
    "text_extraction_latest_update": "2025-10-25T09:18:45.020555Z"
  }
}