{
  "action": {
    "description": "The committee on ECD recommend that the measure be PASSED, WITH AMENDMENTS. The votes were as follows: 6 Ayes: Representative(s) Ilagan, Tam, Templo, Todd, Matsumoto; Ayes with reservations: Representative(s) Hussey;  Noes: none; and 1 Excused: Representative(s) Holt.",
    "date": "2025-03-13",
    "organization_id": "~{\"classification\": \"lower\"}",
    "classification": [
      "committee-passage-favorable"
    ],
    "related_entities": []
  },
  "bill_id": "SB1269"
}