{
  "legislative_session": "2025",
  "identifier": "SB866",
  "title": "RELATING TO EMERGENCY MEDICAL SERVICES.",
  "from_organization": "~{\"classification\": \"upper\"}",
  "classification": [
    "bill"
  ],
  "subject": [
    "Appropriations ($)",
    "DOH",
    "Emergency Medical Services",
    "Program",
    "Reports"
  ],
  "abstracts": [
    {
      "note": "description",
      "abstract": "Requires the Department of Health to establish and implement a program to improve and increase support for emergency medical services in the State.  Requires the Department of Health to submit reports to the Legislature.  Appropriates funds."
    }
  ],
  "other_titles": [],
  "other_identifiers": [],
  "actions": [
    {
      "description": "Referred to HHS, WAM.",
      "date": "2025-01-23",
      "organization_id": "~{\"classification\": \"upper\"}",
      "classification": [
        "referral-committee"
      ],
      "related_entities": [
        {
          "name": "Health and Human Services",
          "entity_type": "organization",
          "organization_id": null
        },
        {
          "name": "Ways and Means",
          "entity_type": "organization",
          "organization_id": null
        }
      ],
      "_processing": {
        "log_file_created": "2025-10-23T18:12:57Z"
      }
    },
    {
      "description": "Passed First Reading.",
      "date": "2025-01-21",
      "organization_id": "~{\"classification\": \"upper\"}",
      "classification": [
        "reading-1"
      ],
      "related_entities": [],
      "_processing": {
        "log_file_created": "2025-10-23T18:12:57Z"
      }
    },
    {
      "description": "Introduced.",
      "date": "2025-01-17",
      "organization_id": "~{\"classification\": \"upper\"}",
      "classification": [
        "introduction"
      ],
      "related_entities": [],
      "_processing": {
        "log_file_created": "2025-10-23T18:12:57Z"
      }
    }
  ],
  "sponsorships": [
    {
      "name": "KANUHA",
      "classification": "primary",
      "entity_type": "person",
      "primary": true,
      "person_id": "~{\"name\": \"KANUHA\"}",
      "organization_id": null
    },
    {
      "name": "CHANG",
      "classification": "primary",
      "entity_type": "person",
      "primary": true,
      "person_id": "~{\"name\": \"CHANG\"}",
      "organization_id": null
    },
    {
      "name": "DECOITE",
      "classification": "primary",
      "entity_type": "person",
      "primary": true,
      "person_id": "~{\"name\": \"DECOITE\"}",
      "organization_id": null
    },
    {
      "name": "GABBARD",
      "classification": "primary",
      "entity_type": "person",
      "primary": true,
      "person_id": "~{\"name\": \"GABBARD\"}",
      "organization_id": null
    },
    {
      "name": "INOUYE",
      "classification": "primary",
      "entity_type": "person",
      "primary": true,
      "person_id": "~{\"name\": \"INOUYE\"}",
      "organization_id": null
    },
    {
      "name": "KIDANI",
      "classification": "primary",
      "entity_type": "person",
      "primary": true,
      "person_id": "~{\"name\": \"KIDANI\"}",
      "organization_id": null
    },
    {
      "name": "MCKELVEY",
      "classification": "primary",
      "entity_type": "person",
      "primary": true,
      "person_id": "~{\"name\": \"MCKELVEY\"}",
      "organization_id": null
    },
    {
      "name": "Richards",
      "classification": "cosponsor",
      "entity_type": "person",
      "primary": false,
      "person_id": "~{\"name\": \"Richards\"}",
      "organization_id": null
    }
  ],
  "related_bills": [],
  "versions": [
    {
      "note": "SB866",
      "links": [
        {
          "url": "https://data.capitol.hawaii.gov/sessions//session2025/bills/SB866_.HTM",
          "media_type": "text/html"
        },
        {
          "url": "https://data.capitol.hawaii.gov/sessions//session2025/bills/SB866_.PDF",
          "media_type": "application/pdf"
        }
      ],
      "date": "",
      "classification": ""
    }
  ],
  "documents": [],
  "citations": [],
  "sources": [
    {
      "url": "https://capitol.hawaii.gov/session/measure_indiv.aspx?billtype=SB&billnumber=866&year=2025",
      "note": ""
    }
  ],
  "extras": {
    "current_referral": "HHS, WAM"
  },
  "jurisdiction": {
    "id": "ocd-jurisdiction/country:us/state:hi/government",
    "name": "Hawaii",
    "classification": "state",
    "division_id": "ocd-division/country:us/state:hi"
  },
  "_processing": {
    "logs_latest_update": "2025-10-23T18:12:57Z",
    "text_extraction_latest_update": "2025-10-24T18:34:48.089552Z"
  }
}