{
  "identifier": "",
  "motion_text": "Report Adopted; Passed Third Reading.",
  "motion_classification": [
    "passage"
  ],
  "start_date": "2025-04-02",
  "result": "pass",
  "organization": "~{\"classification\": \"upper\"}",
  "legislative_session": "2025",
  "bill": "~{\"from_organization__classification\": \"lower\", \"identifier\": \"HB429\", \"legislative_session__identifier\": \"2025\"}",
  "bill_action": null,
  "bill_identifier": "HB429",
  "votes": [
    {
      "option": "not voting",
      "voter_name": "Senator(s",
      "voter_id": "~{\"name\": \"Senator(s\"}",
      "note": ""
    }
  ],
  "counts": [
    {
      "option": "yes",
      "value": 23
    },
    {
      "option": "no",
      "value": 0
    },
    {
      "option": "not voting",
      "value": 2
    }
  ],
  "sources": [
    {
      "url": "https://capitol.hawaii.gov/session/measure_indiv.aspx?billtype=HB&billnumber=429&year=2025",
      "note": ""
    }
  ],
  "extras": {},
  "dedupe_key": "5#HB429#2025-04-02#Report Adopted; Passed Third Reading. Ayes, 23; Aye(s) with reservations: none.  Noes, 0 (none).  Excused, 2 (Senator(s) DeCorte, Ihara).  Transmitted to House."
}