{
  "legislative_session": "2025",
  "identifier": "HB368",
  "title": "RELATING TO MOTOR VEHICLE SUN SCREENING DEVICES.",
  "from_organization": "~{\"classification\": \"lower\"}",
  "classification": [
    "bill"
  ],
  "subject": [
    "Equipment",
    "Exemptions",
    "Motor Vehicles",
    "Safety",
    "Sun Screening Devices",
    "Window Tinting"
  ],
  "abstracts": [
    {
      "note": "description",
      "abstract": "Exempts from restrictions on light transmittance percentages, up to a certain percent, of certain motor vehicle sun screening devices for persons having light sensitivity of the eyes due to a medical condition.  Effective 7/1/3000.  (HD1)"
    }
  ],
  "other_titles": [],
  "other_identifiers": [],
  "actions": [
    {
      "description": "Passed Second Reading as amended in HD 1 and referred to the committee(s) on JHA with none voting aye with reservations; none voting no (0) and Representative(s) Cochran, Ward excused (2).",
      "date": "2025-02-11",
      "organization_id": "~{\"classification\": \"lower\"}",
      "classification": [
        "reading-2",
        "referral-committee"
      ],
      "related_entities": [
        {
          "name": "Judiciary & Hawaiian Affairs",
          "entity_type": "organization",
          "organization_id": null
        }
      ],
      "_processing": {
        "log_file_created": "2025-10-23T18:12:53Z"
      }
    },
    {
      "description": "Reported from TRN (Stand. Com. Rep. No. 368) as amended in HD 1, recommending passage on Second Reading and referral to JHA.",
      "date": "2025-02-11",
      "organization_id": "~{\"classification\": \"lower\"}",
      "classification": [],
      "related_entities": [],
      "_processing": {
        "log_file_created": "2025-10-23T18:12:53Z"
      }
    },
    {
      "description": "The committee on TRN recommend that the measure be PASSED, WITH AMENDMENTS. The votes were as follows: 7 Ayes: Representative(s) Kila, Grandinetti, Evslin, Kitagawa, Miyake, Muraoka, Pierick; Ayes with reservations: none;  Noes: none; and 2 Excused: Representative(s) Cochran, La Chica.",
      "date": "2025-01-30",
      "organization_id": "~{\"classification\": \"lower\"}",
      "classification": [
        "committee-passage-favorable"
      ],
      "related_entities": [],
      "_processing": {
        "log_file_created": "2025-10-23T18:12:53Z"
      }
    },
    {
      "description": "Bill scheduled for decision making on Thursday, 01-30-25 10:30AM in conference room 430 VIA VIDEOCONFERENCE.",
      "date": "2025-01-28",
      "organization_id": "~{\"classification\": \"lower\"}",
      "classification": [],
      "related_entities": [],
      "_processing": {
        "log_file_created": "2025-10-23T18:12:53Z"
      }
    },
    {
      "description": "The committee(s) on TRN recommend(s) that the measure be deferred until 01-30-25 at 10:30 am.",
      "date": "2025-01-28",
      "organization_id": "~{\"classification\": \"lower\"}",
      "classification": [
        "deferral"
      ],
      "related_entities": [],
      "_processing": {
        "log_file_created": "2025-10-23T18:12:53Z"
      }
    },
    {
      "description": "Bill scheduled to be heard by TRN on Tuesday, 01-28-25 10:00AM in House conference room 430 VIA VIDEOCONFERENCE.",
      "date": "2025-01-24",
      "organization_id": "~{\"classification\": \"lower\"}",
      "classification": [],
      "related_entities": [],
      "_processing": {
        "log_file_created": "2025-10-23T18:12:53Z"
      }
    },
    {
      "description": "Referred to TRN, JHA, referral sheet 1",
      "date": "2025-01-21",
      "organization_id": "~{\"classification\": \"lower\"}",
      "classification": [
        "referral-committee"
      ],
      "related_entities": [
        {
          "name": "Transportation",
          "entity_type": "organization",
          "organization_id": null
        },
        {
          "name": "Judiciary & Hawaiian Affairs",
          "entity_type": "organization",
          "organization_id": null
        }
      ],
      "_processing": {
        "log_file_created": "2025-10-23T18:12:53Z"
      }
    },
    {
      "description": "Introduced and Pass First Reading.",
      "date": "2025-01-17",
      "organization_id": "~{\"classification\": \"lower\"}",
      "classification": [
        "introduction",
        "reading-1"
      ],
      "related_entities": [],
      "_processing": {
        "log_file_created": "2025-10-23T18:12:53Z"
      }
    },
    {
      "description": "Pending introduction.",
      "date": "2025-01-16",
      "organization_id": "~{\"classification\": \"lower\"}",
      "classification": [],
      "related_entities": [],
      "_processing": {
        "log_file_created": "2025-10-23T18:12:53Z"
      }
    }
  ],
  "sponsorships": [
    {
      "name": "EVSLIN",
      "classification": "primary",
      "entity_type": "person",
      "primary": true,
      "person_id": "~{\"name\": \"EVSLIN\"}",
      "organization_id": null
    }
  ],
  "related_bills": [],
  "versions": [
    {
      "note": "HB368_HD1",
      "links": [
        {
          "url": "https://data.capitol.hawaii.gov/sessions//session2025/bills/HB368_HD1_.HTM",
          "media_type": "text/html"
        },
        {
          "url": "https://data.capitol.hawaii.gov/sessions//session2025/bills/HB368_HD1_.PDF",
          "media_type": "application/pdf"
        }
      ],
      "date": "",
      "classification": ""
    },
    {
      "note": "HB368",
      "links": [
        {
          "url": "https://data.capitol.hawaii.gov/sessions//session2025/bills/HB368_.HTM",
          "media_type": "text/html"
        },
        {
          "url": "https://data.capitol.hawaii.gov/sessions//session2025/bills/HB368_.PDF",
          "media_type": "application/pdf"
        }
      ],
      "date": "",
      "classification": ""
    }
  ],
  "documents": [],
  "citations": [],
  "sources": [
    {
      "url": "https://capitol.hawaii.gov/session/measure_indiv.aspx?billtype=HB&billnumber=368&year=2025",
      "note": ""
    }
  ],
  "extras": {
    "current_referral": "TRN, JHA"
  },
  "jurisdiction": {
    "id": "ocd-jurisdiction/country:us/state:hi/government",
    "name": "Hawaii",
    "classification": "state",
    "division_id": "ocd-division/country:us/state:hi"
  },
  "_processing": {
    "logs_latest_update": "2025-10-23T18:12:53Z"
  }
}