{
  "legislative_session": "2025",
  "identifier": "HB902",
  "title": "RELATING TO EDUCATION.",
  "from_organization": "~{\"classification\": \"lower\"}",
  "classification": [
    "bill"
  ],
  "subject": [
    "Appropriation ($)",
    "Department of Education",
    "Hawaiian Electric Company",
    "Planned Public Safety Power Shutoff"
  ],
  "abstracts": [
    {
      "note": "description",
      "abstract": "Appropriates funds to the Department of Education to conduct a study on methods to support department schools that may be impacted by electric utilities' planned public safety power shutoff program.  Effective 7/1/3000.  (HD1)"
    }
  ],
  "other_titles": [],
  "other_identifiers": [],
  "actions": [
    {
      "description": "Passed Second Reading as amended in HD 1 and referred to the committee(s) on FIN with Representative(s) Matsumoto, Reyes Oda, Shimizu voting aye with reservations; Representative(s) Garcia, Muraoka, Pierick voting no (3) and Representative(s) Cochran, Sayama, Ward excused (3).",
      "date": "2025-02-12",
      "organization_id": "~{\"classification\": \"lower\"}",
      "classification": [
        "reading-2",
        "referral-committee"
      ],
      "related_entities": [
        {
          "name": "Finance",
          "entity_type": "organization",
          "organization_id": null
        }
      ],
      "_processing": {
        "log_file_created": "2025-10-23T18:13:00Z"
      }
    },
    {
      "description": "Reported from EDN (Stand. Com. Rep. No. 469) as amended in HD 1, recommending passage on Second Reading and referral to FIN.",
      "date": "2025-02-12",
      "organization_id": "~{\"classification\": \"lower\"}",
      "classification": [],
      "related_entities": [],
      "_processing": {
        "log_file_created": "2025-10-23T18:13:00Z"
      }
    },
    {
      "description": "The committee on EDN recommend that the measure be PASSED, WITH AMENDMENTS. The votes were as follows: 10 Ayes: Representative(s) Woodson, La Chica, Amato, Evslin, Garrett, Kapela, Kila, Olds, Sayama, Souza; Ayes with reservations: none; 1 Noes: Representative(s) Muraoka; and  Excused: none.",
      "date": "2025-02-06",
      "organization_id": "~{\"classification\": \"lower\"}",
      "classification": [
        "committee-passage-favorable"
      ],
      "related_entities": [],
      "_processing": {
        "log_file_created": "2025-10-23T18:13:00Z"
      }
    },
    {
      "description": "Bill scheduled to be heard by EDN on Thursday, 02-06-25 2:00PM in House conference room 309 VIA VIDEOCONFERENCE.",
      "date": "2025-02-03",
      "organization_id": "~{\"classification\": \"lower\"}",
      "classification": [],
      "related_entities": [],
      "_processing": {
        "log_file_created": "2025-10-23T18:13:00Z"
      }
    },
    {
      "description": "Referred to EDN, FIN, referral sheet 3",
      "date": "2025-01-23",
      "organization_id": "~{\"classification\": \"lower\"}",
      "classification": [
        "referral-committee"
      ],
      "related_entities": [
        {
          "name": "Education",
          "entity_type": "organization",
          "organization_id": null
        },
        {
          "name": "Finance",
          "entity_type": "organization",
          "organization_id": null
        }
      ],
      "_processing": {
        "log_file_created": "2025-10-23T18:13:00Z"
      }
    },
    {
      "description": "Introduced and Pass First Reading.",
      "date": "2025-01-23",
      "organization_id": "~{\"classification\": \"lower\"}",
      "classification": [
        "introduction",
        "reading-1"
      ],
      "related_entities": [],
      "_processing": {
        "log_file_created": "2025-10-23T18:13:00Z"
      }
    },
    {
      "description": "Pending introduction.",
      "date": "2025-01-21",
      "organization_id": "~{\"classification\": \"lower\"}",
      "classification": [],
      "related_entities": [],
      "_processing": {
        "log_file_created": "2025-10-23T18:13:00Z"
      }
    }
  ],
  "sponsorships": [
    {
      "name": "WOODSON",
      "classification": "primary",
      "entity_type": "person",
      "primary": true,
      "person_id": "~{\"name\": \"WOODSON\"}",
      "organization_id": null
    },
    {
      "name": "AMATO",
      "classification": "primary",
      "entity_type": "person",
      "primary": true,
      "person_id": "~{\"name\": \"AMATO\"}",
      "organization_id": null
    },
    {
      "name": "BELATTI",
      "classification": "primary",
      "entity_type": "person",
      "primary": true,
      "person_id": "~{\"name\": \"BELATTI\"}",
      "organization_id": null
    },
    {
      "name": "GRANDINETTI",
      "classification": "primary",
      "entity_type": "person",
      "primary": true,
      "person_id": "~{\"name\": \"GRANDINETTI\"}",
      "organization_id": null
    },
    {
      "name": "KUSCH",
      "classification": "primary",
      "entity_type": "person",
      "primary": true,
      "person_id": "~{\"name\": \"KUSCH\"}",
      "organization_id": null
    },
    {
      "name": "LOWEN",
      "classification": "primary",
      "entity_type": "person",
      "primary": true,
      "person_id": "~{\"name\": \"LOWEN\"}",
      "organization_id": null
    },
    {
      "name": "MARTEN",
      "classification": "primary",
      "entity_type": "person",
      "primary": true,
      "person_id": "~{\"name\": \"MARTEN\"}",
      "organization_id": null
    },
    {
      "name": "OLDS",
      "classification": "primary",
      "entity_type": "person",
      "primary": true,
      "person_id": "~{\"name\": \"OLDS\"}",
      "organization_id": null
    },
    {
      "name": "POEPOE",
      "classification": "primary",
      "entity_type": "person",
      "primary": true,
      "person_id": "~{\"name\": \"POEPOE\"}",
      "organization_id": null
    },
    {
      "name": "REYES ODA",
      "classification": "primary",
      "entity_type": "person",
      "primary": true,
      "person_id": "~{\"name\": \"REYES ODA\"}",
      "organization_id": null
    },
    {
      "name": "SOUZA",
      "classification": "primary",
      "entity_type": "person",
      "primary": true,
      "person_id": "~{\"name\": \"SOUZA\"}",
      "organization_id": null
    },
    {
      "name": "TAKENOUCHI",
      "classification": "primary",
      "entity_type": "person",
      "primary": true,
      "person_id": "~{\"name\": \"TAKENOUCHI\"}",
      "organization_id": null
    },
    {
      "name": "TAM",
      "classification": "primary",
      "entity_type": "person",
      "primary": true,
      "person_id": "~{\"name\": \"TAM\"}",
      "organization_id": null
    },
    {
      "name": "TARNAS",
      "classification": "primary",
      "entity_type": "person",
      "primary": true,
      "person_id": "~{\"name\": \"TARNAS\"}",
      "organization_id": null
    },
    {
      "name": "TODD",
      "classification": "primary",
      "entity_type": "person",
      "primary": true,
      "person_id": "~{\"name\": \"TODD\"}",
      "organization_id": null
    },
    {
      "name": "WARD",
      "classification": "primary",
      "entity_type": "person",
      "primary": true,
      "person_id": "~{\"name\": \"WARD\"}",
      "organization_id": null
    }
  ],
  "related_bills": [],
  "versions": [
    {
      "note": "HB902_HD1",
      "links": [
        {
          "url": "https://data.capitol.hawaii.gov/sessions//session2025/bills/HB902_HD1_.HTM",
          "media_type": "text/html"
        },
        {
          "url": "https://data.capitol.hawaii.gov/sessions//session2025/bills/HB902_HD1_.PDF",
          "media_type": "application/pdf"
        }
      ],
      "date": "",
      "classification": ""
    },
    {
      "note": "HB902",
      "links": [
        {
          "url": "https://data.capitol.hawaii.gov/sessions//session2025/bills/HB902_.HTM",
          "media_type": "text/html"
        },
        {
          "url": "https://data.capitol.hawaii.gov/sessions//session2025/bills/HB902_.PDF",
          "media_type": "application/pdf"
        }
      ],
      "date": "",
      "classification": ""
    }
  ],
  "documents": [],
  "citations": [],
  "sources": [
    {
      "url": "https://capitol.hawaii.gov/session/measure_indiv.aspx?billtype=HB&billnumber=902&year=2025",
      "note": ""
    }
  ],
  "extras": {
    "current_referral": "EDN, FIN"
  },
  "jurisdiction": {
    "id": "ocd-jurisdiction/country:us/state:hi/government",
    "name": "Hawaii",
    "classification": "state",
    "division_id": "ocd-division/country:us/state:hi"
  },
  "_processing": {
    "logs_latest_update": "2025-10-23T18:13:00Z",
    "text_extraction_latest_update": "2025-10-28T05:11:01.831516Z"
  }
}